<?xml version="1.0" encoding="UTF-8"?>
<map>
<key>CT-17APR-Caltrain-Sunday-01</key>
<value>
<array>
<elem><array>
<elem>20170529</elem><elem>1</elem>
</array></elem><elem><array>
<elem>20170704</elem><elem>1</elem>
</array></elem><elem><array>
<elem>20170804</elem><elem>1</elem>
</array></elem><elem><array>
<elem>20171123</elem><elem>1</elem>
</array></elem><elem><array>
<elem>20171225</elem><elem>1</elem>
</array></elem><elem><array>
<elem>20180101</elem><elem>1</elem>
</array></elem>
</array>
</value><key>CT-17APR-Combo-Weekday-01</key>
<value>
<array>
<elem><array>
<elem>20170529</elem><elem>2</elem>
</array></elem><elem><array>
<elem>20170704</elem><elem>2</elem>
</array></elem><elem><array>
<elem>20170804</elem><elem>2</elem>
</array></elem><elem><array>
<elem>20171123</elem><elem>2</elem>
</array></elem><elem><array>
<elem>20171225</elem><elem>2</elem>
</array></elem><elem><array>
<elem>20180101</elem><elem>2</elem>
</array></elem>
</array>
</value>
</map>
